projectm2_hermine_delamaire/__init__.py
projectm2_hermine_delamaire/blockchain.py
projectm2_hermine_delamaire/broker.py
projectm2_hermine_delamaire/data_module.py
projectm2_hermine_delamaire/metrics.py
projectm2_hermine_delamaire/pybacktestchain.py
projectm2_hermine_delamaire/utils.py
projectm2_hermine_delamaire-0.7.3.dist-info/LICENSE
projectm2_hermine_delamaire-0.7.3.dist-info/METADATA
projectm2_hermine_delamaire-0.7.3.dist-info/WHEEL
projectm2_hermine_delamaire-0.7.3.dist-info/RECORD
