Metadata-Version: 2.1
Name: projectm2-hermine-delamaire
Version: 0.7.3
Summary: Create, analyze, and compare backtesting strategies for financial portfolios. Stores backtest results securely on a blockchain.
License: MIT
Author: Hermine Delamaire
Requires-Python: >=3.10,<4.0
Classifier: License :: OSI Approved :: MIT License
Classifier: Programming Language :: Python :: 3
Classifier: Programming Language :: Python :: 3.10
Classifier: Programming Language :: Python :: 3.11
Requires-Dist: colorama (>=0.4.6,<0.5.0)
Requires-Dist: numpy (>=2.0.1,<3.0.0)
Requires-Dist: pandas (>=2.2.2,<3.0.0)
Requires-Dist: scipy (<1.14.0)
Requires-Dist: sec-cik-mapper (>=2.1.0,<3.0.0)
Requires-Dist: yfinance (>=0.2.41,<0.3.0)
